fiddler_langgraph/VERSION
fiddler_langgraph/__init__.py
fiddler_langgraph/core/__init__.py
fiddler_langgraph/core/attributes.py
fiddler_langgraph/core/client.py
fiddler_langgraph/core/span_processor.py
fiddler_langgraph/tracing/__init__.py
fiddler_langgraph/tracing/callback.py
fiddler_langgraph/tracing/instrumentation.py
fiddler_langgraph/tracing/jsonl_capture.py
fiddler_langgraph/tracing/util.py
fiddler_langgraph-1.3.0.dist-info/METADATA
fiddler_langgraph-1.3.0.dist-info/WHEEL
fiddler_langgraph-1.3.0.dist-info/top_level.txt
fiddler_langgraph-1.3.0.dist-info/RECORD
