Metadata-Version: 2.4
Name: fiddler-langgraph
Version: 1.3.0
Summary: Python SDK for instrumenting GenAI Applications with Fiddler
Author-email: Fiddler AI <support@fiddler.ai>
License-Expression: Apache-2.0
Project-URL: Homepage, https://fiddler.ai
Project-URL: Documentation, https://docs.fiddler.ai
Project-URL: Repository, https://github.com/fiddler-labs/fiddler-sdk
Project-URL: Issues, https://github.com/fiddler-labs/fiddler-sdk/issues
Keywords: fiddler,ai,genai,llm,monitoring,observability,instrumentation,langgraph,langchain,opentelemetry
Classifier: Development Status :: 3 - Alpha
Classifier: Intended Audience :: Developers
Classifier: Topic :: Software Development :: Libraries :: Python Modules
Classifier: Topic :: System :: Monitoring
Classifier: Topic :: Software Development :: Quality Assurance
Classifier: Programming Language :: Python :: 3
Classifier: Programming Language :: Python :: 3.10
Classifier: Programming Language :: Python :: 3.11
Classifier: Programming Language :: Python :: 3.12
Classifier: Programming Language :: Python :: 3.13
Classifier: Operating System :: OS Independent
Requires-Python: >=3.10
Requires-Dist: pip>=21.0
Requires-Dist: opentelemetry-api<=1.39.1,>=1.19.0
Requires-Dist: opentelemetry-sdk<=1.39.1,>=1.19.0
Requires-Dist: opentelemetry-instrumentation<=0.60b1,>=0.40b0
Requires-Dist: opentelemetry-exporter-otlp-proto-http<=1.39.1,>=1.19.0
Requires-Dist: pydantic>=2.0
Provides-Extra: dev
Requires-Dist: pytest>=8.3.5; extra == "dev"
Requires-Dist: pytest-cov>=6.1.1; extra == "dev"
Requires-Dist: mypy>=1.16.1; extra == "dev"
Requires-Dist: black>=25.1.0; extra == "dev"
Requires-Dist: isort>=6.0; extra == "dev"
Requires-Dist: flake8>=7.2.0; extra == "dev"
Requires-Dist: pre-commit>=4.2.0; extra == "dev"
Requires-Dist: bandit>=1.8.5; extra == "dev"
Requires-Dist: pylint>=3.3.7; extra == "dev"
Requires-Dist: ruff>=0.12.0; extra == "dev"
Requires-Dist: nox>=2025.5.1; extra == "dev"
Requires-Dist: tomli==2.2.1; extra == "dev"
Requires-Dist: langgraph<=1.0.1,>=0.3.28; extra == "dev"
Requires-Dist: langchain-community<=1.0.0,>=0.3.27; extra == "dev"
Requires-Dist: langchain-openai<=1.0.0,>=0.2.14; extra == "dev"
Requires-Dist: langchain-chroma<=1.0.0,>=0.1.6; extra == "dev"
Requires-Dist: langgraph-supervisor>=0.0.1; extra == "dev"
